setup.py
z_probability/Binomialdistribution.py
z_probability/Gaussiandistribution.py
z_probability/Generaldistribution.py
z_probability/__init__.py
z_probability.egg-info/PKG-INFO
z_probability.egg-info/SOURCES.txt
z_probability.egg-info/dependency_links.txt
z_probability.egg-info/not-zip-safe
z_probability.egg-info/top_level.txt